MANIFEST.in
README.txt
setup.cfg
setup.py
docs/HISTORY.txt
docs/HISTORY.txt~
docs/INSTALL.txt
docs/LICENSE.GPL
docs/LICENSE.txt
quintagroup/__init__.py
quintagroup.catalogupdater.egg-info/PKG-INFO
quintagroup.catalogupdater.egg-info/SOURCES.txt
quintagroup.catalogupdater.egg-info/dependency_links.txt
quintagroup.catalogupdater.egg-info/entry_points.txt
quintagroup.catalogupdater.egg-info/namespace_packages.txt
quintagroup.catalogupdater.egg-info/not-zip-safe
quintagroup.catalogupdater.egg-info/requires.txt
quintagroup.catalogupdater.egg-info/top_level.txt
quintagroup/catalogupdater/__init__.py
quintagroup/catalogupdater/configure.zcml
quintagroup/catalogupdater/interfaces.py
quintagroup/catalogupdater/overrides.zcml
quintagroup/catalogupdater/tests.py
quintagroup/catalogupdater/utility.py
quintagroup/catalogupdater/exportimport/__init__.py
quintagroup/catalogupdater/exportimport/catalogupdater.py
quintagroup/catalogupdater/exportimport/overrides.zcml
quintagroup/catalogupdater/exportimport/tests/__init__.py
quintagroup/catalogupdater/exportimport/tests/test_catalogupdate.py