Metadata-Version: 1.0
Name: quintagroup.catalogupdater
Version: 0.1.1
Summary: Package for controlled ZCatalog object updating
Home-page: http://svn.quintagroup.com/products/quintagroup.catalogupdater
Author: Quintagroup
Author-email: support@quintagroup.com
License: GPL
Keywords: catalog update plone quintagroup
Platform: UNKNOWN
Classifier: Framework :: Plone
Classifier: Programming Language :: Python
